{
    "page": {
        "label": "TRANSLATE.CONFIG.TITLE"
    },
    "sections": [
        {
            "id": "settings",
            "element": "section",
            "label": "TRANSLATE.CONFIG.SETTINGS",
            "icon": "fa-cog",
            "onSave": {
                "type": "controller",
                "endpoint": "music_service/planet_radio",
                "method": "updateConfig"
            },
            "saveButton": {
                "label": "TRANSLATE.CONFIG.SAVE",
                "data": [
                    "username",
                    "password",
                    "metadata_delay"
                ]
            },
            "content": [
                {
                    "id": "username",
                    "element": "input",
                    "label": "TRANSLATE.CONFIG.USERNAME",
                    "description": "TRANSLATE.CONFIG.AUTH_DESCRIPTION",
                    "placeholder": "TRANSLATE.CONFIG.USERNAME_PLACEHOLDER",
                    "value": ""
                },
                {
                    "id": "password",
                    "element": "input",
                    "label": "TRANSLATE.CONFIG.PASSWORD",
                    "placeholder": "TRANSLATE.CONFIG.PASSWORD_PLACEHOLDER",
                    "value": "",
                    "type": "password"
                }
            ]
        },
        {
            "id": "info",
            "element": "section",
            "label": "TRANSLATE.CONFIG.ABOUT",
            "icon": "fa-info-circle",
            "description": "TRANSLATE.CONFIG.DESCRIPTION"
        }
    ]
}